char_collection/__init__.py
char_collection/collect.py
char_collection/collect_password.py
tests/__init__.py
tests/collect_password_test.py
tests/collect_test.py
char_collection-1.2.0.dist-info/LICENSE
char_collection-1.2.0.dist-info/METADATA
char_collection-1.2.0.dist-info/WHEEL
char_collection-1.2.0.dist-info/top_level.txt
char_collection-1.2.0.dist-info/RECORD
