Metadata-Version: 2.1
Name: char-collection
Version: 1.2.0
Summary: Building random characters
Home-page: https://github.com/Beloslav13/char-collection
Author: Beloslav
Author-email: velislav1329@gmail.com
License: UNKNOWN
Platform: UNKNOWN
Classifier: Programming Language :: Python :: 3
Classifier: License :: OSI Approved :: MIT License
Classifier: Operating System :: OS Independent
Requires-Python: >=3.6
